dexat/__init__.py
dexat2-2.dist-info/METADATA
dexat2-2.dist-info/WHEEL
dexat2-2.dist-info/top_level.txt
dexat2-2.dist-info/RECORD
