Metadata-Version: 2.1
Name: dexat2
Version: 2
Summary: Dependency confiuse Attack
Author: dex tester
Author-email: <bughunt250@gmail.com
Requires-Dist: requests
Requires-Dist: discord
